s1290166_learn/__init__.py
s1290166_learn/statistics/__init__.py
s1290166_learn/statistics/itemFequencies.py
s1290166_learn/visualization/__init__.py
s1290166_learn/visualization/heatMap.py
s1290166_learn-0.1.0.dist-info/LICENSE.txt
s1290166_learn-0.1.0.dist-info/METADATA
s1290166_learn-0.1.0.dist-info/WHEEL
s1290166_learn-0.1.0.dist-info/top_level.txt
s1290166_learn-0.1.0.dist-info/RECORD
